youtube_gemini_mcp/__init__.py
youtube_gemini_mcp/files_uploader.py
youtube_gemini_mcp/gemini_client.py
youtube_gemini_mcp/server.py
youtube_gemini_mcp/session_manager.py
youtube_gemini_mcp/youtube_validator.py
youtube_gemini_mcp-0.1.1.dist-info/LICENSE
youtube_gemini_mcp-0.1.1.dist-info/METADATA
youtube_gemini_mcp-0.1.1.dist-info/WHEEL
youtube_gemini_mcp-0.1.1.dist-info/entry_points.txt
youtube_gemini_mcp-0.1.1.dist-info/RECORD
